tempeh/__init__.py
tempeh/abstract.py
tempeh/configurations.py
tempeh/constants.py
tempeh/datasets/__init__.py
tempeh/datasets/base_wrapper.py
tempeh/datasets/blob_dataset_retriever.py
tempeh/datasets/blob_datasets.py
tempeh/datasets/compas_datasets.py
tempeh/datasets/seaphe_datasets.py
tempeh/datasets/sk_datasets.py
tempeh/datasets/sparse_datasets.py
tempeh/datasets/uci_dataset_cleaner.py
tempeh/datasets/uci_datasets.py
tempeh/execution/__init__.py
tempeh/execution/azureml/__init__.py
tempeh/execution/azureml/environment_setup.py
tempeh/execution/azureml/workspace.py
tempeh/models/__init__.py
tempeh/models/base_model.py
tempeh/models/decision_tree.py
tempeh/models/keras_model.py
tempeh/models/lightgbm_model.py
tempeh/models/logistic_model.py
tempeh/models/pytorch_model.py
tempeh/models/random_forest_classifier.py
tempeh/models/random_forest_regressor.py
tempeh/models/ridge_model.py
tempeh/models/svm_model.py
tempeh/models/xgboost_model.py
tempeh/perf_utilities/__init__.py
tempeh/perf_utilities/memory.py
tempeh/perf_utilities/munge.py
tests/__init__.py
tests/conftest.py
tests/test_tempeh.py
tempeh-0.1.12.dist-info/LICENSE
tempeh-0.1.12.dist-info/METADATA
tempeh-0.1.12.dist-info/WHEEL
tempeh-0.1.12.dist-info/top_level.txt
tempeh-0.1.12.dist-info/RECORD
