Metadata-Version: 2.1
Name: tempeh
Version: 0.1.12
Summary: Machine Learning Performance Testing Framework
Home-page: https://github.com/microsoft/tempeh
Author: Roman Lutz
Author-email: rolutz@microsoft.com
License: UNKNOWN
Platform: UNKNOWN
Classifier: Programming Language :: Python :: 3
Classifier: License :: OSI Approved :: MIT License
Classifier: Operating System :: OS Independent
Requires-Dist: memory-profiler
Requires-Dist: numpy
Requires-Dist: pandas
Requires-Dist: pytest
Requires-Dist: requests
Requires-Dist: scipy
Requires-Dist: shap
Requires-Dist: scikit-learn
